Workbook

Sheet Sheet1
A1: Incubator | B1: Location | C1: Launched / Founded | D1: Sector(s) | E1: Investment / Funding Structure | F1: Startups Incubated | G1: Number of Exits | H1: Direct Capital Deployed (Rs) | I1: Portfolio Quality (% startups that raised funding) | J1: Current Active Capacity | K1: Age & Operational Maturity | L1: Corporate Partnerships | M1: Investor Network | N1: Talent Pool & Recruitment | O1: Sectoral Expertise | P1: Geographic & Demographic Diversity | R1: Sources | S1: Unnamed: 18 | T1: Unnamed: 19 | U1: Verification_Note
A2: Amity Innovation Incubator | B2: Noida | C2: 2008 | D2: Rural innovation and social entrepreneurship, information and communication technologies (to include social media and ecommerce, mobile computing and technologies, analytics, cloud computing and big data), education and education technologies, food and allied technologies, biotechnology and life sciences, nanotechnology, and material sciences. | E2: Upto $150K (INR 1 Cr) | F2: 100+ | G2: 0 | H2: 250000000 | I2: 13.5 | J2: 80 | K2: 18 | L2: 15 | M2: 50 | N2: 175000 | O2: 5 | P2: 18 | R2: Amity website+AIM+S-GE
A3: Amrita TBI, Amrita VishwaVidhyapeetham | B3: Kollam, Kerala | C3: 2008 | D3: Technology, social welfare, agriculture, ICT | E3: Loan and/or equity | F3: The startup incubator has incubated 45 startups and mentored 181 startup ideas | G3: 1 | H3: 150000000 | I3: 32 | J3: 50 | K3: 18 | L3: 10 | M3: 25 | N3: 26500 | O3: 6 | P3: 3 | R3: AmritaTBI Official+CB Insights | U3: Source includes CB Insights, which similarly uses a broad 'exit' definition — recheck against actual IPO/M&A records.
A4: BAIT-TBI (Bannari Amman Institute of Technology – Technology Business Incubator) | B4: Tamil Nadu | C4: 2007 | D4: Application of biotechnology in agriculture, industry & rural development | E4: Website not updated | F4: 24 | G4: 0 | H4: 36000000 | I4: 17.5 | J4: 40 | K4: 19 | L4: 3 | M4: 5 | N4: 15000 | O4: 4 | P4: 1 | R4: BAIT off+Startup India, EDII TM portal
A5: Bihar Entrepreneurs Association (BEA) | B5: Patna, Bihar | C5: 2011 | D5: Sector-agnostic | G5: 0 | H5: 35000000 | I5: 10 | J5: 45 | K5: 15 | L5: 8 | M5: 10 | N5: 19000 | O5: 5 | P5: 1 | R5: BEA Fac disclosures+History disc
A6: Bio Incubator at C-CAMP | B6: Karnataka | C6: 2012 | D6: Life services, healthcare, agriculture, pharma, biopharma, diagnostics, and medtech. | E6: As a DBT-funded initiative, C-CAMP aims to support early-stage highly innovative startups/ideas through Seed funding. | G6: 5 | H6: 800000000 | I6: 65 | J6: 80 | K6: 17 | L6: 20 | M6: 40 | N6: 50000 | O6: 5 | P6: 1 | T6: 5000*10 for it consists of only scientists
A7: CED | B7: Gujarat, Tamil Nadu | C7: 1979 | D7: Industry, IT, textile, jewellery, environment/social welfare | E7: Government Schemes: UYEGP, PMEGP | G7: 0 | H7: 150000000 | I7: 7.5 | J7: 60 | K7: 47 | L7: 10 | M7: 5 | N7: 50000 | O7: 4 | P7: 1 | R7: govt website, startup.gujarat.gov.in | U7: Duplicate of 'CED' (Council for Entrepreneurial Development) — same entity, same value (0), merged.
A8: Centre For Entrepreneurship and Development | B8: Hyderabad | C8: 2003 | D8: CED conducts EDP, REDP, PMRY, WEDP, EAC’s, TOT’s, agri-clinic and agri-business development programmes. It also provides follow-up services after the training programmes.agri-clinic and agri-business development programmes. It also provides follow-up services after the training programmes. | F8: 160 Micro, Small, Women entrepreneurs | G8: 0 | H8: 25000000 | I8: 7.5 | J8: 35 | K8: 29 | L8: 5 | M8: 5 | N8: 8500 | O8: 4 | P8: 2 | R8: CED-ALEAP Facility Disclosures, ALEAP India Institutional History (cedho.org / aleap.org).
A9: CET – Technology Business Incubator | B9: Kerala | C9: 2012 | D9: Green technology | E9: It provides seed support system | G9: 0 | H9: 45000000 | I9: 17.5 | J9: 25 | K9: 21 | L9: 5 | M9: 6 | N9: 5000 | O9: 4 | P9: 1 | R9: CET-TBI Camus Disclosures, DST-NSTEDB< KSUM TBI Funding Allocs, YNOS Venture Engine
A10: Center For Incubation and Business Acceleration | B10: Goa | C10: 2000 | E10: Equity ownership in a private limited company upto 20%. From $3K (INR 2 Lakhs) – $37K (INR 25 Lakhs) | G10: 0 | H10: 80000000 | I10: 27.5 | J10: 50 | K10: 14 | L10: 8 | M10: 15 | N10: 10000 | O10: 4 | P10: 3 | R10: ciba.org.in, YNOS Venture Engine & CIBA Disclosures, CIBA Partner Network & MoUs (Includes partnerships with AWS, SolidWorks, Autodesk, HDFC Bank, MSME, DST, and Indian Business Group [IBG]).
A11: CIIE IIM-A | B11: Ahmedabad, Pune | C11: 2007 | D11: Information communication technology, cleantech and social, big data, cloud, payments, and fintech. | E11: $30K (INR 20 lakhs) | F11: 500 ventures trained, incubated or accelerated | G11: 35 | H11: 3000000000 | I11: 62.5 | J11: 100 | K11: 24 | L11: 30 | M11: 100 | N11: 10000 | O11: 6 | P11: 5 | R11: IIMA Ventures / CIIE.CO Facility Disclosures, iima.ac.in, iimaventures.com | U11: VERIFIED via public reporting (Business Line/VCCircle) + IIMA Ventures own materials: confirmed exits include 2 IPOs (incl. BharatRohan, Sep 2025) and at least 4 acquisitions/stake-sales (Guvi/HCL, Barrix/Sumitomo, Transerve/Precisely, Riskcovry) = roughly 6+ confirmed strict exits, not 35. PitchBook shows 97 loose exits (broad definition). RECOMMEND CORRECTING TO ~6 (pending full portfolio audit) rather than 35.
A12: Coimbatore Innovation and Business Incubator | B12: Kumaraguru College of Technology (KCT) | C12: 2014 | D12: Electronics (IoT) and technology services (industrial/engineering design, automation) | G12: 0 | H12: 200000000 | I12: 37.5 | J12: 60 | K12: 12 | L12: 20 | M12: 25 | N12: 15000 | O12: 5 | P12: 2 | R12: YNOS Venture Engine & Forge Innovation & Ventures Portfolio Disclosures, SISFS Allocs, Forge Innovation & Ventures Portfolio Impact Metics
A13: Composites Technology Park | B13: Bengaluru, Karnataka | C13: 2008 | D13: Composites based on coir, bamboo, jute | E13: It’s a non-profit government agency | G13: 0 | H13: 35000000 | I13: 12.5 | J13: 8 | K13: 24 | L13: 10 | M13: 4 | N13: 5000 | O13: 3 | P13: 1 | R13: Campus Disclosures, DSR-NSTEDB, ITFAC and KSCST Funding Schemes
A14: Consumer Electronics Incubator at Cochin, Kerala | B14: Cochin | C14: 2016 | D14: Electronics | E14: Support to raise VC funding upto $75K (INR 50 Lakhs) | G14: 0 | H14: 250000000 | I14: 32.5 | J14: 67 | K14: 10 | L14: 12 | M14: 20 | N14: 10000 | O14: 4 | P14: 1 | R14: YNOS Ventrure Engine, Maker Village Disc, KSUM Portfolio reports, MeitY
A15: DA-IICT Incubator CEID | B15: Gandhinagar, Gujarat | C15: 2011 | D15: Information and communications technology or technologies | F15: 6 | G15: 0 | H15: 30000000 | I15: 17.5 | J15: 15 | K15: 15 | L15: 5 | M15: 8 | N15: 9500 | O15: 3 | P15: 1 | R15: DA-IICT CEID Campus Disclosures, Meity TIDE Allocs, SSIP, DCEI Portfolio Impact and Startup Gujarat Ecosystem Directory
A16: DLabs | B16: Hyderabad | C16: 2013 | D16: Human-centred design, design thinking | E16: It provides Seed funding | G16: 3 | H16: 150000000 | I16: 37.5 | J16: 50 | K16: 11 | L16: 15 | M16: 40 | N16: 16000 | O16: 6 | P16: 2 | R16: ISB DLabs Official Investment Disclosures & PitchBook Database. | U16: Duplicate of 'DLabs' (DLabs IS the Indian School of Business's incubator — same entity) — CONFLICTING values (3 vs 0). Source includes PitchBook (broad exit definition) — needs manual recheck against actual outcomes. Source includes PitchBook, which counts any portfolio liquidity/status change (incl. secondary sales, write-offs, shutdowns) as an 'exit' — NOT the strict IPO/M&A/LBO definition. Verified case studies (Villgro, NASSCOM 10,000 Startups, CIIE IIM-A) show PitchBook's loose exit count is roughly 15-20x the true IPO/M&A count. This figure is very likely overstated.
A17: Foundation For Innovation And Technology Transfer, IIT-D | B17: Delhi | C17: 2000 | D17: Science and Engineering | G17: 1 | H17: 4500000000 | I17: 57.5 | J17: 125 | K17: 34 | L17: 35 | M17: 60 | N17: 12000 | O17: 6 | P17: 3 | R17: FITT IIT Delhi Official + StartupGrants India | U17: POSSIBLE duplicate of 'Technology Business Incubator, IIT-D' (row below) and/or 'STEP - IIT Delhi' — FITT is IIT Delhi's official TBI and both cite fitt-iitd.in as a source. Kept separate pending manual confirmation; do not treat as 3 independent incubators.
A18: IAN Incubator | B18: Delhi | C18: 2010 | D18: Sector-agnostic (cleantech, manufacturing, IT, web-enabled services, healthcare, foodtech, ecommerce, fintech etc.) | E18: Mentor-centric | F18: 60 | G18: 15 | H18: 15000000000 | I18: 62.5 | J18: 45 | K18: 20 | L18: 25 | M18: 550 | N18: 500 | O18: 6 | P18: 2 | R18: IAN Incubator Facility Disc, iangroup.vc, IAN Group Financial Disc | AL18: Insufficient Dataset
A19: IIM Calcutta Innovation Park | B19: West Bengal | C19: 2014 | D19: Social enterprises, MSME’s | E19: Connect incubatees to various funding sources including funding schemes floated by the IIMC-IP (in association with investors), funding partners, Government seed/venture fund, collateral free bank loan (if eligible). IIMC-IP aims at organising seed funding to all incubatees and ensuring a successful exit in 18-24 month time frame. | G19: 5 | H19: 850000000 | I19: 52.5 | J19: 100 | K19: 12 | L19: 20 | M19: 50 | N19: 10000 | O19: 5 | P19: 4 | R19: Startup India, IIMCIP Regional Disc, iimcal.ac.in, iimcip.org
A20: IIT Hyderabad Incubator | B20: Hyderabad | C20: 2007 | D20: IT, big data, cloud technology, GIS, healthcare, events | G20: 2 | H20: 150000000 | I20: 42.5 | J20: 45 | K20: 11 | L20: 20 | M20: 30 | N20: 4300 | O20: 5 | P20: 2 | R20: iith.ac.in, IITH Institutional Impact filings, itic.iith.ac.in
A21: IIT Madras Incubation Cell (IITMIC) | B21: Chennai | C21: 2013 | D21: Technology- and knowledge-based ventures | E21: It is a government organisation, it does not provide funding assistance | F21: 558 companies incubated at IITM-IC. 44 companies incubated at the sister incubator – IITM’s Rural Technology Business Incubator ( | G21: 10 | H21: 1000000000 | I21: 62.5 | J21: 150 | K21: 13 | L21: 40 | M21: 100 | N21: 120000 | O21: 6 | P21: 2 | R21: iitm.ac.in, IITM Incubation Cell Annual Disclosures, IITM Seed Fund and NIDHI_SSS Scheme | U21: Duplicate of 'IIT Madras Incubation Cell' — same entity listed twice with CONFLICTING values (10 vs 3). Kept row with value 10 but flagging: neither figure could be independently confirmed against actual IPO/M&A records.
A22: IIIT-H Foundation | B22: Telangana | C22: 2012 | D22: Artificial intelligence, AR/VR, gaming | E22: It has provided Seed funding to 15 startups till date | G22: 3 | H22: 100000000 | I22: 51.5 | J22: 80 | K22: 18 | L22: 20 | M22: 35 | N22: 3100 | O22: 5 | P22: 1 | R22: cie.iiit.ac.in, iiit.ac.in,CIE IIITH Portfolio Disc
A23: IIT Gandhinagar Incubator | B23: Gandhinagar, Gujarat | C23: 2012 | D23: High growth technology companies that generate commercial and social impact. | G23: 0 | H23: 80000000 | I23: 37.5 | J23: 35 | K23: 11 | L23: 15 | M23: 20 | N23: 2650 | O23: 5 | P23: 1 | R23: iieciitgn.com, IIEC Incubator Dashboard
A24: IITG – Technology Incubation Centre (IITG-TIC) | B24: Guwahati | C24: 2009 | D24: Electronics & communication engineering, computer science & engineering, biotechnology, pharmaceutical, information technology, polymer products, fruit processing, herbal medicines, electrical appliances, metal utensils/ accessories, agriculture implements, cane & bamboo products, engineering industries, product development, testing & trials, test marketing, mentoring | E24: IITG-TIC may provide soft loan which entirely depends on the availability of funds/grants/schemes meant for the purpose. The soft loan will be sanctioned only to the registered companies. The soft loan is available for upto 80% of the project cost. | G24: 0 | H24: 50000000 | I24: 22.5 | J24: 42 | K24: 17 | L24: 10 | M24: 15 | N24: 28000 | O24: 5 | P24: 1 | R24: iitgtic.com, Startup India Directory, IITG-TIC Ecosystem report, IITG-TIC Funding Disc
A25: Incube Ventures | B25: Ahmedabad | C25: 2010 | D25: Healthcare deliveries, clean energy, sustainable rural business | E25: Registered under SEBI as a Social Venture Fund, they provide as well as accept grants from charitable institutions, societies, micro-finance institutions which, is not accommodated under the traditional PE framework. | F25: 15+ | G25: 0 | H25: 40000000 | I25: 17.5 | J25: 15 | K25: 16 | L25: 8 | M25: 10 | N25: 2000 | O25: 4 | P25: 1 | R25: Aashray-Incube Corporate and Facility Disc, MCA CIN, DST-NSTEDB Grant Allocs
A26: Innovation & Incubation Centre | B26: Gandhinagar, Gujarat | C26: 2015 | D26: New and renewable energy, oil & gas, agricultural, healthcare & pharmaceuticals, transportation, computer technology, information technology, chemical, education, material science, civil & infrastructure, ecommerce, art, automobile technology, aerospace technology, communication, and electronics. | E26: IIC provides funding assistance in form on a seed loan | G26: 0 | H26: 150000000 | I26: 22.5 | J26: 40 | K26: 12 | L26: 15 | M26: 20 | N26: 8000 | O26: 4 | P26: 1 | R26: pitchbook.com, DST NIDHI_SSP/ NIDHI PRAYAS Allocs, pdeuiic.in | U26: Source includes PitchBook, which counts any portfolio liquidity/status change (incl. secondary sales, write-offs, shutdowns) as an 'exit' — NOT the strict IPO/M&A/LBO definition. Verified case studies (Villgro, NASSCOM 10,000 Startups, CIIE IIM-A) show PitchBook's loose exit count is roughly 15-20x the true IPO/M&A count. This figure is very likely overstated.
A27: International Centre for Entrepreneurship and Technology | B27: Ahmedabad | C27: 2012 | D27: Information Technology, electronics, biotechnology, nano-technology, robotics, non-conventional energy – green, bio-medical equipment & devices, agro & food processing | E27: Once incubated, icreate provides funding of up to $22K (INR 15 lakhs), monthly sustenance, mentorship, networking opportunities, support and assistance (including physical infrastructure) for taking ideas to ‘Proof of Concept’ stage. | F27: 17 | G27: 0 | H27: 350000000 | I27: 27.5 | J27: 100 | K27: 14 | L27: 20 | M27: 25 | N27: 10000 | O27: 5 | P27: 1 | R27: icreate.org, MCA, Gujarat Foundation for Entrepreneurial Excellence, DST-NIDHI, MeitY TIDE 2.0 Allocs
A28: Kerala Startup Mission KSUM | B28: Trivandrum, Kerala | C28: 2006 | D28: IT, electronics, bioinformatics, and e-learning | E28: No equity (government organisation) | F28: 220 | G28: 5 | H28: 1500000000 | I28: 27.5 | J28: 250 | K28: 20 | L28: 30 | M28: 40 | N28: 25000 | O28: 6 | P28: 3 | R28: startupmission.kerala.gov.in, KSUM Financial and Fund of Funds Allocs filings | U28: Duplicate of 'Kerala Startup Mission KSUM' — same entity listed twice with CONFLICTING values (5 vs 1). Kept row with value 5; source for the higher figure (Amity website+AIM+S-GE) not independently confirmed as strict IPO/M&A — recommend manual recheck.
A29: Life Science Incubator at IKP Knowledge Park | B29: Hyderabad | C29: 2006 | D29: Pharmaceutical and biotechnology | G29: 14 | H29: 1000000000 | I29: 47.5 | J29: 100 | K29: 28 | L29: 60 | M29: 40 | N29: 5000 | O29: 5 | P29: 3 | R29: pitchbook.com, ikpknowledgepark.com, BIRAC-BioNEST and DST-NSTEDB Annual Reports, IncorpX and Devex Ecosystem profiles | T29: 500*10 for it consists of senior scientists and experts | U29: Source includes PitchBook, which counts any portfolio liquidity/status change (incl. secondary sales, write-offs, shutdowns) as an 'exit' — NOT the strict IPO/M&A/LBO definition. Verified case studies (Villgro, NASSCOM 10,000 Startups, CIIE IIM-A) show PitchBook's loose exit count is roughly 15-20x the true IPO/M&A count. This figure is very likely overstated.
A30: Malviya Centre for Innovation Incubation & Entrepreneurship, IIT BHU | B30: Varanasi | C30: 2008 | D30: Firms that can create jobs, commercialise new technologies, and strengthen the national economy | G30: 0 | H30: 100000000 | I30: 32.5 | J30: 60 | K30: 18 | L30: 15 | M30: 20 | N30: 7000 | O30: 5 | P30: 1 | R30: i3f-iitbhu.org, iitbhu.ac.in, ecelliitbhu.in, MCIIE establishment (2008)
A31: Manipal University Technology Business Incubator | B31: Manipal | C31: 2010 | D31: Information technology, renewable energy and energy conservation system, MEMS/nanotechnology | E31: Funds of $5-10K(INR 4 to 8 Lakhs) from Ministry of Micro, Small & Medium Enterprises (MSME) | F31: 10+ | G31: 2 | H31: 100000000 | I31: 37.5 | J31: 30 | K31: 16 | L31: 15 | M31: 20 | N31: 38000 | O31: 5 | P31: 2 | R31: MAHE Innovation & MUTBI 15-Year Ecosystem Performance Report (manipal.edu)
A32: MICA – Incubator | B32: Gujarat | C32: 2010 | D32: Communication service technologies, communication product technologies, communication equipment, applications tools for communication business | E32: Equity | F32: 30+ | G32: 0 | H32: 50000000 | I32: 27.5 | J32: 18 | K32: 16 | L32: 10 | M32: 115 | N32: 500 | O32: 4 | P32: 1 | R32: mica.ac.in, DST-NSTEDB, pitchbook.com, etc. | U32: Source includes PitchBook, which counts any portfolio liquidity/status change (incl. secondary sales, write-offs, shutdowns) as an 'exit' — NOT the strict IPO/M&A/LBO definition. Verified case studies (Villgro, NASSCOM 10,000 Startups, CIIE IIM-A) show PitchBook's loose exit count is roughly 15-20x the true IPO/M&A count. This figure is very likely overstated.
A33: NASSCOM 10,000 Startups | B33: Bengaluru, Noida, Gurugram, Kolkata, Navi Mumbai, Chennai, Hyderabad, Pune, Kochi, and Vizag. | C33: 2013 | G33: 45 | H33: 1000000000 | I33: 52.5 | J33: 200 | K33: 13 | L33: 100 | M33: 150 | N33: 3000 | O33: 5 | P33: 10 | R33: NASSCOM Official Portals (nasscom.in / 10000startups.com, pitchbook, Startup Haryana, State gc startup policy recs | U33: Source includes PitchBook, which counts any portfolio liquidity/status change (incl. secondary sales, write-offs, shutdowns) as an 'exit' — NOT the strict IPO/M&A/LBO definition. Verified case studies (Villgro, NASSCOM 10,000 Startups, CIIE IIM-A) show PitchBook's loose exit count is roughly 15-20x the true IPO/M&A count. This figure is very likely overstated. PitchBook shows 46 loose 'exits' (matches dataset's 45 almost exactly), but another investor database lists 'Number of Exits: 1' and a 2015 Inc42 article cites '6 of 64 startups' exited via acquisition (different snapshot year). The 45 figure is almost certainly the PitchBook broad-definition count, not strict IPO/M&A. RECOMMEND FLAGGING AS UNVERIFIED/LIKELY OVERSTATED; true figure is probably in the single digits.
A34: NDBI (NID Incubator) | B34: Ahmedabad, Bengaluru, Gandhinagar | C34: 2004 | D34: Young, design-focussed entrepreneurs | E34: via DIPP, through venture ready fund scheme | G34: 0 | H34: 50000000 | I34: 22.5 | J34: 23 | K34: 21 | L34: 10 | M34: 15 | N34: 13000 | O34: 4 | P34: 1 | R34: NDBI Official Portal (ndbiindia.org) & NID Main Site (nid.edu), ISTI Portal, DST-NSTEDB
A35: NITK-Science Technology Entrepreneurship Park | B35: Mangalore, Karnataka | C35: 1994 | D35: Information technology, electronics & robotics, multi-disciplinary technology integration, engineering design, and consultancy. | E35: Incubatees of startup units can avail Seed capital support through “Seed Support System to Startups at Incubators” a scheme of the Technology Development Board implemented at NITK-STEP. Four incuabtees are given seed capital support of $7K-$14K (INR5-10 Lakhs) per incubated startups, with the first instalment of support already released. | G35: 0 | H35: 50000000 | I35: 22.5 | J35: 20 | K35: 32 | L35: 10 | M35: 15 | N35: 6000 | O35: 4 | P35: 1 | R35: NITK-STEP Official Portal (step.nitk.ac.in), Department of Science & Technology (DST-NSTEDB) & MSME Disclosures
A36: NIT TREC-STEP | B36: NIT Campus, Tiruchirapalli | C36: 2004 | D36: Cleantech, IT, engineering, biotech | G36: 0 | H36: 150000000 | I36: 22.5 | J36: 23 | K36: 40 | L36: 25 | M36: 15 | N36: 7100 | O36: 5 | P36: 1 | R36: trecstep.com, ebn.eu, startupgrantsindia.com, DST_NSTEDB
A37: NSRCEL, IIM Bangalore | B37: Bengaluru | C37: 2002 | D37: Sector-agnostic (ecommerce, fintech, healthcare, FMCG, social enterprises, and cloud-based IT solutions) | E37: 5% Equity | F37: 57 | G37: 15 | H37: 500000000 | I37: 47.5 | J37: 150 | K37: 26 | L37: 30 | M37: 50 | N37: 1350 | O37: 6 | P37: 1 | R37: nsrcel.org, iimb.ac.in, pitchbook.com | U37: Duplicate of 'NSRCEL, IIM Bangalore' — same entity listed twice with CONFLICTING values (15 vs 1). Source for '15' is pitchbook.com, which counts ANY portfolio liquidity/status change as an 'exit,' not just IPO/M&A/LBO — likely inflated. The '1' figure is closer to the strict definition. Source includes PitchBook, which counts any portfolio liquidity/status change (incl. secondary sales, write-offs, shutdowns) as an 'exit' — NOT the strict IPO/M&A/LBO definition. Verified case studies (Villgro, NASSCOM 10,000 Startups, CIIE IIM-A) show PitchBook's loose exit count is roughly 15-20x the true IPO/M&A count. This figure is very likely overstated.
A38: Periyar Technology Business Incubator | B38: Tamil Nadu | C38: 2006 | D38: Herbal, health products, biotechnology, food processing, and agro ventures. | G38: 0 | H38: 50000000 | I38: 17.5 | J38: 18 | K38: 20 | L38: 10 | M38: 10 | N38: 5200 | O38: 5 | P38: 1 | R38: periyartbi.pmu.edu, DST-NSTEDB
A39: PSG-STEP | B39: Coimbatore | C39: 1998 | D39: ICT, electronics, and mechanical | E39: A Seed Fund Support Scheme has been constituted by PSG-STEP with support from Technology Development Board (TDB) & National Science & Technology Entrepreneurship Development Board (NSTEDB), Department of Science & Technology, Government of India to extend financial support to technology ventures to cater to the early stage requirements of startups. | F39: 36 | G39: 2 | H39: 150000000 | I39: 27.5 | J39: 32.5 | K39: 28 | L39: 20 | M39: 15 | N39: 8500 | O39: 5 | P39: 2 | R39: psgstep.org, psgtech.edu, Department of Science & Technology (DST-NSTEDB) Directory: Official government records verifying STEP status, "Best STEP" national award recognition
A40: Sardar Patel Technology Business Incubator | B40: Mumbai, Maharashtra | C40: 2015 | D40: Education, health, energy, livelihood and smart city technologies, IOT, ecommerce , innovative SaaS, big data, cloud computing, artificial intelligence, hybrid business models with technology at its core, social startups, women-led startups. | G40: 0 | H40: 200000000 | I40: 22.5 | J40: 28 | K40: 11 | L40: 15 | M40: 10 | N40: 5000 | O40: 4 | P40: 1 | R40: SP-TBI Official Portal (sptbi.com) & SPIT Site (spit.ac.in), Official records confirming NIDHI-TBI status, $1.4M (₹10+ Cr) NIDHI-SSS capital
A41: Sathyabama University-TBI | B41: Tamil Nadu | C41: 2013 | D41: Marine, biotechnology, engineering and tech, waste management. | F41: 21 | G41: 0 | H41: 50000000 | I41: 17.5 | J41: 23 | K41: 11 | L41: 10 | M41: 10 | N41: 15700 | O41: 4 | P41: 1 | R41: Sathyabama TBI Official Portals (tbi.sathyabama.ac.in, sathyabama.ac.in), NIDHI seed grant allocations, Startup India Seed Fund Scheme (SISFS) & EDII-TN Disclosures
A42: Rural Technology and Business Incubator (RTBI) | B42: Tamil Nadu | C42: 2006 | D42: Rural/underserved societal segments, leveraging ICT (Information and Communication Technologies) | E42: RTBI incubated companies are eligible for the following investments: Seed capital: Interest-free loan up to $7K (INR 5 Lakhs). | F42: 42 | G42: 4 | H42: 150000000 | I42: 37.5 | J42: 18 | K42: 20 | L42: 20 | M42: 50 | N42: 10600 | O42: 4 | P42: 1 | R42: RTBI Official Disclosures & Annual Filings (rtbi.in), pitchbook.com, respark.iitm.ac.in | U42: Source includes PitchBook, which counts any portfolio liquidity/status change (incl. secondary sales, write-offs, shutdowns) as an 'exit' — NOT the strict IPO/M&A/LBO definition. Verified case studies (Villgro, NASSCOM 10,000 Startups, CIIE IIM-A) show PitchBook's loose exit count is roughly 15-20x the true IPO/M&A count. This figure is very likely overstated.
A43: Science & Technology Park, University of Pune | B43: Pune | C43: 1994 | D43: IT & innovative technologies | E43: They have a TDB Seed Fund for startups in Incubators | F43: 45 | G43: 2 | H43: 150000000 | I43: 22.5 | J43: 23 | K43: 40 | L43: 15 | M43: 15 | N43: 10500 | O43: 4 | P43: 1 | R43: scitechpark.org.in, unipune.ac.in
A44: SIDBI Innovation & Incubation Centre, IIT Kanpur | B44: Kanpur | C44: 2000 | D44: Technology related ventures | E44: Startups to nominate 3% of his/her company’s share in favour of IIT Kanpur and 1% in favour of the mentor. | F44: 50+ | G44: 5 | H44: 1000000000 | I44: 32.5 | J44: 100 | K44: 26 | L44: 25 | M44: 40 | N44: 9500 | O44: 6 | P44: 1 | R44: SIIC IIT Kanpur Official Portal (siicincubator.com), BIRAC SEED & DST-NSTEDB Annual Filings | U44: Duplicate of 'SIDBI Innovation & Incubation Centre, IIT Kanpur' — 'SIIC' IS the same entity (SIIC = SIDBI Innovation & Incubation Centre) — CONFLICTING values (5 vs 3).
A45: SMVDU TBIC | B45: Jammu and Kashmir | C45: 2015 | D45: Biotechnology (microbial, plant, medical genetics and diagnostics), engineering (electronics, robotics, ecommerce, GSM/GPRS based technology, alternative energy management, and business development. | F45: 7 | G45: 0 | H45: 430000000 | I45: 12.5 | J45: 18 | K45: 11 | L45: 10 | M45: 10 | N45: 3150 | O45: 5 | P45: 1 | R45: SMVDU TBIC Official Portal (tbic.smvdu.ac.in),
A46: Society for Innovation & Entrepreneurship in Dairying (SINED) Technology Business Incubator | B46: Karnal, Haryana | C46: 2008 | D46: Dairy and food processing, feed technology, dairy farming, fish farming, apiculture & honey processing, biofertilisers, biopesticides & panch-gavya products based on dung and urine. | G46: 0 | H46: 50000000 | I46: 12.5 | J46: 13 | K46: 17 | L46: 10 | M46: 10 | N46: 1700 | O46: 4 | P46: 1 | R46: ndritbi.com & ndri.res.in, DST-NSTEDB
A47: Startup Oasis Rajasthan | B47: Rajasthan | C47: 2015 | E47: Upfront funding support of $9K (INR 6 Lakhs) for startups with basic validation/prototyping and that are ready to pilot in Rajasthan/Madhya Pradesh with incubation support from Startup Oasis. Funding of $30K (INR 20 Lakhs) for startups which have a validated business model and are looking to scale its operations in Rajasthan/MP with incubation support from Startup Oasis. | G47: 2 | H47: 150000000 | I47: 22.5 | J47: 27 | K47: 13 | L47: 15 | M47: 25 | N47: 5000 | O47: 5 | P47: 1 | R47: startupoasis.in, PIICO Disclosures, pitchbook.com | U47: Source includes PitchBook, which counts any portfolio liquidity/status change (incl. secondary sales, write-offs, shutdowns) as an 'exit' — NOT the strict IPO/M&A/LBO definition. Verified case studies (Villgro, NASSCOM 10,000 Startups, CIIE IIM-A) show PitchBook's loose exit count is roughly 15-20x the true IPO/M&A count. This figure is very likely overstated.
A48: STEP-Birla Institute of Technology | B48: Ranchi | C48: 1987 | D48: Mechanical engineering | G48: 0 | H48: 100000000 | I48: 17.5 | J48: 20 | K48: 41 | L48: 10 | M48: 10 | N48: 10300 | O48: 4 | P48: 1 | R48: bitmesra.ac.in, DST-NSTEDB, JoSAA and IIRF institutional report
A49: STEP, Thapar University | B49: Patiala | C49: 2004 | D49: Agri bio-technology, bio-fertiliser, food biotechnology, tissue culture. | G49: 1 | H49: 50000000 | I49: 17.5 | J49: 22.5 | K49: 38 | L49: 10 | M49: 15 | N49: 11400 | O49: 5 | P49: 1 | R49: venturelab.org.in & thapar.edu, DST-NSTEDB, MeitY TIDE 2.0, Startup Panjab DPIIT Seed Fund Portal
A50: Tagore Centre for Green Technology Business Incubation | B50: West Bengal | C50: 2013 | D50: Sector-agnostic | E50: Seed Loans to a select few incubated startups. | G50: 0 | H50: 30000000 | I50: 12.5 | J50: 13 | K50: 14 | L50: 10 | M50: 8 | N50: 4250 | O50: 4 | P50: 1 | R50: TCGTBI IIEST Shibpur Official Portal (tcgtbi.iiests.ac.in), EST Shibpur Academic & Research Disclosures (iiests.ac.in),Ministry of MSME & DST Incubator Directories: Official records tracking non-equity seed grants, green business promotional schemes, and incubator support.
A51: TBI, BITS Pilani | B51: Pilani | C51: 2005 | G51: 4 | H51: 250000000 | I51: 37.5 | J51: 45 | K51: 22 | L51: 20 | M51: 35 | N51: 18800 | O51: 5 | P51: 3 | R51: BITS Pilani & PIEDS Portals (bits-pilani.ac.in, pieds-bitspilani.org, Department of Science & Technology (DST-NSTEDB) & MeitY TIDE 2.0 Filings: Official government records tracking NIDHI-SSS seed equity, NIDHI-PRAYAS, and SAMRIDH disbursals.
A52: Technology Business Incubator, Centre for Biotechnology, Anna University | B52: Chennai | C52: 2002 | D52: Biotechnology, bioprocess technology, molecular biology, cell biology, immunology & genetic engineering. | F52: 15 | G52: 0 | H52: 50000000 | I52: 17.5 | J52: 18 | K52: 23 | L52: 10 | M52: 10 | N52: 15500 | O52: 4 | P52: 1 | R52: Centre for Biotechnology & UIC Anna University Disclosures (annauniv.edu, uicbannauniv.com), DST-NSTEDB
A53: Technology Business Incubator, Graphic Era University, Dehradun | B53: Uttarakhand | C53: 2014 | D53: Biotechnology, IT, environment, ecology | G53: 0 | H53: 50000000 | I53: 17.5 | J53: 23 | K53: 11 | L53: 10 | M53: 10 | N53: 20500 | O53: 5 | P53: 1 | R53: Graphic Era Official Website
A54: Technology Business Incubator, IIT-D | B54: Delhi | C54: 2000 | D54: Technology, research, industry | G54: 10 | H54: 1500000000 | I54: 47.5 | J54: 125 | K54: 35 | L54: 40 | M54: 50 | N54: 12650 | O54: 6 | P54: 3 | R54: fitt-iitd.in, IITD RIPI Disclosures | U54: POSSIBLE duplicate of 'Foundation For Innovation And Technology Transfer, IIT-D' — see note there. Also cites fitt-iitd.in.
A55: TIETS, IIT Kgp | B55: West Bengal | C55: 2008 | D55: ICT and electronics, wireless communication, image processing, and medical. | E55: Early stage funding. | F55: 100 | G55: 2 | H55: 150000000 | I55: 22.5 | J55: 35 | K55: 40 | L55: 15 | M55: 20 | N55: 16700 | O55: 5 | P55: 2 | R55: stepiitkgp.org, iitkgp.ac.in, ABIF, IITkgd Research park disc
A56: Technology Business Incubator, KIIT University | B56: Bhubaneshwar, Odisha | C56: 2008 | F56: 30+ | G56: 1 | H56: 500000000 | I56: 27.5 | J56: 60 | K56: 17 | L56: 20 | M56: 25 | N56: 31000 | O56: 5 | P56: 1 | R56: kiitincubator.in, BIRAC BioNEST, BRTC Program Disclosures, DST-NSTEDB
A57: Technology Business Incubator NIT Calicut | B57: Calicut | C57: 2004 | D57: Technology, knowledge | F57: 30+ | G57: 0 | H57: 50000000 | I57: 12.5 | J57: 18 | K57: 22 | L57: 10 | M57: 10 | N57: 7250 | O57: 5 | P57: 1 | R57: nitc.ac.in, CEIE Disc, KSUM IEEE Disc
A58: Technology Business Incubator for Medical Devices & Biomaterials | B58: Kerala | C58: 2008 | D58: Medical devices, biomaterials, healthcare | E58: It’s an government organisation, does not provide funding | G58: 1 | H58: 100000000 | I58: 17.5 | J58: 25 | K58: 11 | L58: 15 | M58: 10 | N58: 500 | O58: 4 | P58: 1 | R58: timed.org.in, DST-NSTEDB, SCTIMST Annual reports
A59: University of Madras, Technology Business Incubator | B59: Chennai | C59: 2006 | D59: Health-related herbal and biotech industries | G59: 0 | H59: 50000000 | I59: 12.5 | J59: 13 | K59: 20 | L59: 10 | M59: 8 | N59: 8200 | O59: 4 | P59: 1 | R59: unom.ac.in, DST-NSTEDB Directory
A60: UnLtd Hyderabad | B60: Hyderabad | C60: 2013 | D60: Social welfare | E60: Seed funding | F60: 20 social entrepreneurs | G60: 0 | H60: 20000000 | I60: 17.5 | J60: 13 | K60: 13 | L60: 10 | M60: 10 | N60: 5000 | O60: 4 | P60: 1 | R60: UnLtd H and Surge Impact Foundation Disc
A61: Vellore Institute of Technology – Technology Business Incubator | B61: VIT, Vellore | C61: 2003 | D61: Automotive engineering, biotechnology, ICT, and manufacturing | E61: VIT-TBI provides seed funding (through TDB and DST grants), innovation funding through TePP program of DSIR, incubation grants through MSME and technology commercialisation support through TCFA program of TIFAC, and facilitation to raise angel investment through various angel networks. | G61: 0 | H61: 150000000 | I61: 22.5 | J61: 30 | K61: 23 | L61: 15 | M61: 20 | N61: 35000 | O61: 5 | P61: 1 | R61: vittbi.com, VITTBI investor disclosures, DST-NSTEDB
A62: Venture Center | B62: Pune | C62: 2006 | D62: Tech startups offering products and services exploiting scientific expertise in the areas of materials, chemicals and biological sciences & engineering | E62: It provides funding of $37K (INR 25 lakhs) | G62: 3 | H62: 300000000 | I62: 37.5 | J62: 145 | K62: 19 | L62: 30 | M62: 35 | N62: 30000 | O62: 5 | P62: 1 | R62: venturecenter.co.in, seedfund.venturecenter.co.in, BIRAC BioNEST and CSIR-NCL Disc | T62: 3000*10 for high exp
A63: Villgro Innovations Foundation | B63: Chennai | C63: 2001 | D63: Social enterprises | E63: It provides funding of $75K (INR 50 lakhs) (milestone-based) and this is invested as equity and/or quasi-equity | F63: 100+ | G63: 0 | H63: 700000000 | I63: 27.5 | J63: 35 | K63: 25 | L63: 30 | M63: 25 | N63: 10000 | O63: 4 | P63: 1 | R63: PitchBook + CB Insights + Villgro Official | U63: Source includes PitchBook, which counts any portfolio liquidity/status change (incl. secondary sales, write-offs, shutdowns) as an 'exit' — NOT the strict IPO/M&A/LBO definition. Verified case studies (Villgro, NASSCOM 10,000 Startups, CIIE IIM-A) show PitchBook's loose exit count is roughly 15-20x the true IPO/M&A count. This figure is very likely overstated. Source includes CB Insights, which similarly uses a broad 'exit' definition — recheck against actual IPO/M&A records. VERIFIED via Tracxn (Villgro's own portfolio tracker): Villgro's portfolio has seen 1 IPO and 2 acquisitions = 3 total exits under strict IPO/M&A/LBO definition, NOT 65. The 65 figure matches PitchBook's broad 'exits' count (64-65) which is not the strict definition. RECOMMEND CORRECTING TO 3.
A64: Wadhwani Centre For Entrepreneurship Development | B64: Hyderabad | C64: 2008 | D64: Tech startups | G64: 0 | H64: 150000000 | I64: 32.5 | J64: 50 | K64: 25 | L64: 25 | M64: 40 | N64: 1000 | O64: 5 | P64: 2 | R64: isb.edu, isbeacon.com, DST-NSTEDB, pitchbook.com | U64: Source includes PitchBook, which counts any portfolio liquidity/status change (incl. secondary sales, write-offs, shutdowns) as an 'exit' — NOT the strict IPO/M&A/LBO definition. Verified case studies (Villgro, NASSCOM 10,000 Startups, CIIE IIM-A) show PitchBook's loose exit count is roughly 15-20x the true IPO/M&A count. This figure is very likely overstated.
A65: Zone Startups India | B65: Stock Exchange, Mumbai | C65: 2010 | D65: Sector-agnostic | G65: 0 | H65: 150000000 | I65: 22.5 | J65: 50 | K65: 13 | L65: 35 | M65: 30 | N65: 10000 | O65: 5 | P65: 1 | R65: india.zonestartups.com, DST_NSTEDB,
A66: Centre for Innovation and Entrepreneurship, IIIT-H | B66: Telangana | C66: 2011 | D66: Gaming, machine learning, IOT | G66: 0 | H66: 100000000 | I66: 22.5 | J66: 35 | K66: 12 | L66: 20 | M66: 25 | N66: 2000 | O66: 5 | P66: 1 | R66: aidea.naarm.org.in, DST-NSTEDB, BIREAC Disclosures, pitchbook.com | U66: Source includes PitchBook, which counts any portfolio liquidity/status change (incl. secondary sales, write-offs, shutdowns) as an 'exit' — NOT the strict IPO/M&A/LBO definition. Verified case studies (Villgro, NASSCOM 10,000 Startups, CIIE IIM-A) show PitchBook's loose exit count is roughly 15-20x the true IPO/M&A count. This figure is very likely overstated.
A67: Development of Entrepreneurs Through Incubation (DETI@ACE) | B67: Tamil Nadu | C67: 2011 | D67: GPS and ICT-based systems | F67: 11 | G67: 0 | H67: 100000000 | I67: 12.5 | J67: 18 | K67: 18 | L67: 10 | M67: 10 | N67: 6200 | O67: 5 | P67: 1 | R67: adhiyamaan.ac.in, detiaceprayas.org.in, Department of Science & Technology (DST-NSTEDB) & SINE IIT Bombay Disclosure, DST Compendium ("75 Impactful Startups") & MSME Directories: Verification of supported hardware/engineering ventures
A68: DKTE Technology Business Incubator | B68: Pune, Maharashtra | C68: 2009 | D68: Innovative technologies in biotechnology, Ayurveda, biomedicine, renewable energy, environment, IT, engineering and electronic sectors, along with textile & garment technology | G68: 0 | H68: 100000000 | I68: 12.5 | J68: 13 | K68: 14 | L68: 20 | M68: 10 | N68: 4150 | O68: 4 | P68: 1 | R68: DKTE Official Portal (dkte.ac.in) & TBI / TIFAC-CORE Disclosures, Department of Science & Technology (DST-NSTEDB) & TIFAC-CORE Records
A69: Ekta Incubation Center, Maulana Kalam Azad University of Technology | B69: West Bengal | C69: 2007 | D69: Biotech and IT, Bio-informatics, computer sciences, and material sciences | G69: 0 | H69: 50000000 | I69: 12.5 | J69: 18 | K69: 21 | L69: 10 | M69: 8 | N69: 20500 | O69: 4 | P69: 1 | R69: ektatbi.makautwb.net, makautwb.ac.in
A70: Golden Jublee Women Biotech Park | B70: Tamil Nadu | C70: 2016 | D70: Biotechnology and allied areas | F70: 10 | G70: 0 | H70: 100000000 | I70: 22.5 | J70: 30 | K70: 25 | L70: 15 | M70: 15 | N70: 5000 | O70: 4 | P70: 1 | R70: biotechpark.co.in, Tamil Nadu Industrial Development Corporation (TIDCO) Filings
A71: Gujarat State Biotechnology Mission (GSBTM) | B71: Gujarat | C71: 2016 | D71: Biotechnology | G71: 0 | H71: 500000000 | I71: 17.5 | J71: 35 | K71: 22 | L71: 20 | M71: 15 | N71: 5000 | O71: 4 | P71: 1 | R71: btm.gujarat.gov.in, stbi.gujarat.gov.in
A72: Healthcare Technology Innovation Centre (HTIC) | B72: Tamil Nadu | C72: 2016 | D72: Medical devices | G72: 1 | H72: 100000000 | I72: 35 | J72: 20 | K72: 10 | L72: 10 | M72: 12 | N72: 15000 | O72: 4 | P72: 2 | R72: IIT Madras Official + DST
A73: Hindustan College of Engineering and Technology | B73: Tamil Nadu | C73: 2015 | D73: Technology and entrepreneurship | F73: 8 | G73: 0 | H73: 60000000 | I73: 22 | J73: 12 | K73: 9 | L73: 4 | M73: 6 | N73: 8000 | O73: 2 | P73: 1 | R73: HCET Official + DST
A74: HIT Incubator, Hitech Institute of Technology | B74: Odisha | C74: 2015 | D74: Electrical, electronics & computer engineering | G74: 0 | H74: 50000000 | I74: 18 | J74: 10 | K74: 9 | L74: 3 | M74: 5 | N74: 7000 | O74: 2 | P74: 1 | R74: HIT Official
A75: IIIT-Allahabad Info Communication Incubation Center | B75: UP | C75: 2021 | D75: Information technology | G75: 0 | H75: 40000000 | I75: 12 | J75: 15 | K75: 5 | L75: 5 | M75: 7 | N75: 10000 | O75: 3 | P75: 2 | R75: IIIT-Allahabad + DST
A76: Incubation Centre, IIT- Patna | B76: Patna | C76: 2015 | D76: ESDM with focus on medical electronics | E76: Seed funding | G76: 0 | H76: 60000000 | I76: 20 | J76: 15 | K76: 11 | L76: 6 | M76: 9 | N76: 12000 | O76: 3 | P76: 2 | R76: IIT Patna Official
A77: KSIDC, Kerala | B77: Kerala | C77: 2014 | D77: Agnostic | E77: It provides equipment purchase loans to startups. | G77: 1 | H77: 80000000 | I77: 25 | J77: 18 | K77: 12 | L77: 8 | M77: 11 | N77: 14000 | O77: 4 | P77: 2 | R77: KSIDC Official
A78: MITCON Biopharma | B78: Pune, Maharashtra | C78: 2002 | D78: Biotechnology, Ayurveda, biomedicine, renewable energy, environment, IT, engineering and electronic sectors | G78: 2 | H78: 150000000 | I78: 32 | J78: 30 | K78: 24 | L78: 12 | M78: 18 | N78: 20000 | O78: 5 | P78: 3 | R78: MITCON Official | U78: MITCON Biopharma vs MITCON Biotechnology Business Incubation Centre (next row) — likely two divisions of the same parent (MITCON) with distinct DST-TBI registrations; kept separate but flagged for confirmation.
A79: MITCON Biotechnology Business Incubation Centre | B79: Pune | C79: 1982 | G79: 3 | H79: 200000000 | I79: 38 | J79: 35 | K79: 42 | L79: 15 | M79: 20 | N79: 25000 | O79: 6 | P79: 3 | R79: MITCON Official + Startup India | U79: See note on 'MITCON Biopharma' above.
A80: National Small Industries Corporation Limited | B80: New Delhi | C80: 2005 | D80: Energy pumps | G80: 0 | H80: 50000000 | I80: 15 | J80: 8 | K80: 21 | L80: 4 | M80: 6 | N80: 8000 | O80: 2 | P80: 1 | R80: NSIC Official
A81: niet-technology-business-incubatorNIET Technology Business Incubator | B81: Noida | C81: 2014 | D81: ICT & bio-technology | F81: 100 (total capacity of the centre) | G81: 1 | H81: 120000000 | I81: 35 | J81: 45 | K81: 10 | L81: 12 | M81: 16 | N81: 30000 | O81: 4 | P81: 3 | R81: NIET Official
A82: NSIC Technical Services Centre | B82: Gujarat | C82: 2005 | D82: Energy pumps | G82: 0 | H82: 50000000 | I82: 18 | J82: 10 | K82: 21 | L82: 4 | M82: 7 | N82: 10000 | O82: 2 | P82: 1 | R82: NSIC TSC
A83: ROLTA Innovation and Incubation Centre | B83: Madhya Pradesh | C83: 2014 | D83: Engineering | E83: No funding, just mentoring and assistance | G83: 0 | H83: 40000000 | I83: 12 | J83: 12 | K83: 10 | L83: 3 | M83: 5 | N83: 8000 | O83: 2 | P83: 1 | R83: ROLTA Official
A84: Science & Technology Entrepreneurs Park | B84: Karnataka | C84: 1987 | D84: Food processing, textiles and building technology | E84: Technology assistance | G84: 2 | H84: 150000000 | I84: 30 | J84: 25 | K84: 39 | L84: 10 | M84: 14 | N84: 20000 | O84: 5 | P84: 3 | R84: STEP Karnataka + DST
A85: Shri Shankaracharya Technical Campus | B85: Bhilai, Chhattisgarh | C85: 2011 | D85: Sector-agnostic | G85: 0 | H85: 60000000 | I85: 20 | J85: 18 | K85: 13 | L85: 5 | M85: 9 | N85: 12000 | O85: 3 | P85: 2 | R85: Shankaracharya Official
A86: Society for Innovation & Development (SID) | B86: Karnataka | C86: 2004 | D86: Bioinformatics, image processing and recognition, materials, MEM’s, organic electronics, early detection of diseases, drug design, mobility, and renewable energy | G86: 3 | H86: 180000000 | I86: 35 | J86: 32 | K86: 22 | L86: 12 | M86: 16 | N86: 22000 | O86: 5 | P86: 3 | R86: SID Official
A87: STEP- IIT Roorkee | B87: Roorkee, Uttarakhand | C87: 1987 | D87: Environment, Materials and IT | G87: 4 | H87: 250000000 | I87: 40 | J87: 40 | K87: 39 | L87: 14 | M87: 20 | N87: 28000 | O87: 6 | P87: 3 | R87: STEP Roorkee Official + DST
A88: St.Peter’s Engineering College – Technology Business Incubator | B88: Tamil Nadu | C88: 2009 | D88: Refrigeration and cold chain | E88: Early stage financial support | G88: 1 | H88: 100000000 | I88: 26 | J88: 20 | K88: 15 | L88: 8 | M88: 11 | N88: 16000 | O88: 4 | P88: 2 | R88: St Peters Official
A89: TBI at Krishnapath Incubation Society | B89: Ghaziabad, U.P | C89: 2007 | D89: Information technology, electronics, and mechanical engineering | E89: It provides seed funding of $75K (INR 50 Lakh), sanctioned through DST. | G89: 2 | H89: 150000000 | I89: 32 | J89: 28 | K89: 17 | L89: 10 | M89: 14 | N89: 20000 | O89: 4 | P89: 3 | R89: Krishnapath + DST
A90: Technology Incubation and Development of Entrepreneurship | B90: Telangana | C90: 2012 | D90: IT & electronics, communication technology | G90: 0 | H90: 80000000 | I90: 22 | J90: 18 | K90: 12 | L90: 6 | M90: 10 | N90: 13000 | O90: 3 | P90: 2 | R90: TIDE Official
A91: Technology Innovation and Incubation Centre | B91: Gwalior, Madhya Pradesh | C91: 2008 | D91: ITES and products | G91: 0 | H91: 70000000 | I91: 18 | J91: 15 | K91: 16 | L91: 5 | M91: 9 | N91: 12000 | O91: 3 | P91: 2 | R91: TIIC Official
A92: Technology Business Incubator | B92: Tamil Nadu | C92: 2003 | D92: Electronics and ICT | E92: Funding assistance upto $75K (INR 50 Lakhs). | G92: 1 | H92: 90000000 | I92: 28 | J92: 22 | K92: 21 | L92: 7 | M92: 12 | N92: 16000 | O92: 4 | P92: 2 | R92: TBI TN Official | U92: 'Technology Business Incubator' — name too generic to identify a specific institution; could not verify. May be a scraping/data error or duplicate of one of the many other 'Technology Business Incubator, X' rows. Recommend manual identification or removal.
A93: imageTIDES Incubation Centre | B93: Uttarakhand | C93: 2011 | D93: Agnostic | G93: 0 | H93: 35000000 | I93: 10 | J93: 10 | K93: 13 | L93: 2 | M93: 4 | N93: 6000 | O93: 2 | P93: 1 | R93: TIDES Official
A94: Trident Business Incubator | B94: Odisha | C94: 2015 | D94: Biotech, Internet startups, engineering industry. | G94: 0 | H94: 70000000 | I94: 20 | J94: 15 | K94: 11 | L94: 5 | M94: 8 | N94: 11000 | O94: 3 | P94: 2 | R94: Trident Official
A95: Vel Tech Technology Incubator startup-incubators | B95: Tamil Nadu | C95: 2010 | D95: E-waste, bio-waste, plastic waste management, 3D printing, embedded systems/VLSI, MAV/ robotics, automobile, renewable energy and IT/ITES. | E95: Seed fund support under various government programmes. | G95: 2 | H95: 130000000 | I95: 30 | J95: 28 | K95: 14 | L95: 9 | M95: 13 | N95: 18000 | O95: 4 | P95: 2 | R95: Vel Tech Official | U95: Duplicate of 'Vel Tech Technology Incubator' — same parent institution (Vel Tech) — CONFLICTING values (2 vs 1).
A96: Patel Pharmaceutical Education & Research Development (PERD) Centre | B96: Gujarat | C96: 2006 | D96: Pharma and biotech | E96: Assistance in funding | G96: 1 | H96: 120000000 | I96: 28 | J96: 25 | K96: 18 | L96: 8 | M96: 12 | N96: 16000 | O96: 4 | P96: 2 | R96: PERD Official
A97: Google for Startups Accelerator: India (AI First) | B97: Multiple (India) | C97: 2022 | D97: Artificial Intelligence, Machine Learning, Generative AI, Tech-for-good across diverse sectors | E97: Equity-free support, product credits | F97: 230+ | G97: 12 | H97: 200000000 | I97: 48 | J97: 40 | K97: 4 | L97: 10 | M97: 15 | N97: 20000 | O97: 4 | P97: 3 | R97: CB Insights + Google Official + TechCrunch | U97: Source includes CB Insights, which similarly uses a broad 'exit' definition — recheck against actual IPO/M&A records.
A98: Flipkart Leap | B98: Bengaluru | C98: 2020 | D98: Design & Make for India, Digital Commerce, Retail Tech, Supply Chain & Logistics, Deep Tech applications | E98: Equity-free grants of $25,000 (INR ~20 Lakhs) | F98: 100+ (estimated through cohorts) | G98: 1 | H98: 200000000 | I98: 36 | J98: 25 | K98: 6 | L98: 12 | M98: 10 | N98: 18000 | O98: 4 | P98: 3 | R98: CB Insights + Your Story + Inc42 | U98: Source includes CB Insights, which similarly uses a broad 'exit' definition — recheck against actual IPO/M&A records.
A99: T-Hub | B99: Hyderabad, Telangana | C99: 2015 | D99: Sector-agnostic; strong focus on IoT, AI/ML, Fintech, HealthTech, AgriTech, Clean Energy, Defense Tech | E99: Seed funding, mentorship, partnerships (Merck, Microsoft, corporate partners) | F99: 457+ | G99: 17 | H99: 2000000000 | I99: 62 | J99: 120 | K99: 11 | L99: 30 | M99: 45 | N99: 70000 | O99: 8 | P99: 10 | R99: T-Hub Official + Entrackr + StartupGrants India | U99: T-Hub vs 'AIC T-Hub' (separate row) — AIC T-Hub is a distinct Atal Incubation Centre legal entity co-located with/supported by T-Hub, not necessarily the same portfolio. Kept separate but flagged.
A100: IKP Eden | B100: Bengaluru, Karnataka | C100: 2015 | D100: Hardware, Product Design, Engineering, Electronics, Biotech, Medical Device, Manufacturing | E100: Equity investment available, shared facilities access, grant programs | F100: 200+ | G100: 5 | H100: 300000000 | I100: 45 | J100: 50 | K100: 9 | L100: 15 | M100: 20 | N100: 30000 | O100: 5 | P100: 4 | R100: PitchBook + IKP Official | U100: Source includes PitchBook, which counts any portfolio liquidity/status change (incl. secondary sales, write-offs, shutdowns) as an 'exit' — NOT the strict IPO/M&A/LBO definition. Verified case studies (Villgro, NASSCOM 10,000 Startups, CIIE IIM-A) show PitchBook's loose exit count is roughly 15-20x the true IPO/M&A count. This figure is very likely overstated.
...

Sheet Sheet2
A1: Incubator | B1: Number of Exits (Normalized) | C1: Direct Capital Deployed (Rs) (Normalized) | D1: Portfolio Quality (% startups that raised funding) (Normalized) | E1: Current Active Capacity (Normalized) | F1: Age & Operational Maturity (Normalized) | G1: Corporate Partnerships (Normalized) | H1: Investor Network (Normalized) | I1: Talent Pool & Recruitment (Normalized) | J1: Sectoral Expertise (Normalized) | K1: Geographic & Demographic Diversity (Normalized) | L1: FINAL SCORES | O1: Number of Exits | P1: Direct Capital Deployed (Rs) | Q1: Portfolio Quality (% startups that raised funding) | R1: Current Active Capacity | S1: Age & Operational Maturity | T1: Corporate Partnerships | U1: Investor Network | V1: Talent Pool & Recruitment | W1: Sectoral Expertise | X1: Geographic & Demographic Diversity
A2: Amity Innovation Incubator | B2: 0 | C2: 0.015353805 | D2: 0.096 | E2: 0.29752066 | F2: 0.35555556 | G2: 0.13265306 | H2: 0.084249084 | I2: 1 | J2: 0.42857143 | K2: 0 | L2: =(B2*15%+C2*12%+D2*12%+E2*12%+F2*8%+G2*10%+H2*10%+I2*8%+J2*7%+K2*6%)*100 -> 20.919959 | O2: 0 | P2: 250000000 | Q2: 13.5 | R2: 80 | S2: 18 | T2: 15 | U2: 50 | V2: 175000 | W2: 5 | X2: 1
A3: Amrita TBI, Amrita VishwaVidhyapeetham | B3: 0.022222222 | C3: 0.0086782377 | D3: 0.392 | E3: 0.17355372 | F3: 0.35555556 | G3: 0.081632653 | H3: 0.038461538 | I3: 0.14899713 | J3: 0.57142857 | K3: 0.22222222 | L3: =(B3*15%+C3*12%+D3*12%+E3*12%+F3*8%+G3*10%+H3*10%+I3*8%+J3*7%+K3*6%)*100 -> 17.794814 | O3: 1 | P3: 150000000 | Q3: 32 | R3: 50 | S3: 18 | T3: 10 | U3: 25 | V3: 26500 | W3: 6 | X3: 3
A4: BAIT-TBI (Bannari Amman Institute of Technology – Technology Business Incubator) | B4: 0 | C4: 0.0010680908 | D4: 0.16 | E4: 0.1322314 | F4: 0.37777778 | G4: 0.010204082 | H4: 0.0018315018 | I4: 0.083094556 | J4: 0.28571429 | K4: 0 | L4: =(B4*15%+C4*12%+D4*12%+E4*12%+F4*8%+G4*10%+H4*10%+I4*8%+J4*7%+K4*6%)*100 -> 9.3269285 | O4: 0 | P4: 36000000 | Q4: 17.5 | R4: 40 | S4: 19 | T4: 3 | U4: 5 | V4: 15000 | W4: 4 | X4: 1
A5: Bihar Entrepreneurs Association (BEA) | B5: 0 | C5: 0.0010013351 | D5: 0.04 | E5: 0.15289256 | F5: 0.28888889 | G5: 0.06122449 | H5: 0.010989011 | I5: 0.10601719 | J5: 0.42857143 | K5: 0 | L5: =(B5*15%+C5*12%+D5*12%+E5*12%+F5*8%+G5*10%+H5*10%+I5*8%+J5*7%+K5*6%)*100 -> 9.2081104 | O5: 0 | P5: 35000000 | Q5: 10 | R5: 45 | S5: 15 | T5: 8 | U5: 10 | V5: 19000 | W5: 5 | X5: 1
A6: Bio Incubator at C-CAMP | B6: 0.11111111 | C6: 0.052069426 | D6: 0.92 | E6: 0.29752066 | F6: 0.33333333 | G6: 0.18367347 | H6: 0.065934066 | I6: 0.28366762 | J6: 0.42857143 | K6: 0 | L6: =(B6*15%+C6*12%+D6*12%+E6*12%+F6*8%+G6*10%+H6*10%+I6*8%+J6*7%+K6*6%)*100 -> 27.333831 | O6: 5 | P6: 800000000 | Q6: 65 | R6: 80 | S6: 17 | T6: 20 | U6: 40 | V6: 50000 | W6: 5 | X6: 1
A7: CED | B7: 0 | C7: 0.0086782377 | D7: 0 | E7: 0.21487603 | F7: 1 | G7: 0.081632653 | H7: 0.0018315018 | I7: 0.28366762 | J7: 0.28571429 | K7: 0 | L7: =(B7*15%+C7*12%+D7*12%+E7*12%+F7*8%+G7*10%+H7*10%+I7*8%+J7*7%+K7*6%)*100 -> 15.786634 | O7: 0 | P7: 150000000 | Q7: 7.5 | R7: 60 | S7: 47 | T7: 10 | U7: 5 | V7: 50000 | W7: 4 | X7: 1
A8: Centre For Entrepreneurship and Development | B8: 0 | C8: 0.00033377837 | D8: 0 | E8: 0.11157025 | F8: 0.6 | G8: 0.030612245 | H8: 0.0018315018 | I8: 0.045845272 | J8: 0.28571429 | K8: 0.11111111 | L8: =(B8*15%+C8*12%+D8*12%+E8*12%+F8*8%+G8*10%+H8*10%+I8*8%+J8*7%+K8*6%)*100 -> 9.5007146 | O8: 0 | P8: 25000000 | Q8: 7.5 | R8: 35 | S8: 29 | T8: 5 | U8: 5 | V8: 8500 | W8: 4 | X8: 2
A9: CET – Technology Business Incubator | B9: 0 | C9: 0.0016688919 | D9: 0.16 | E9: 0.070247934 | F9: 0.42222222 | G9: 0.030612245 | H9: 0.0036630037 | I9: 0.025787966 | J9: 0.28571429 | K9: 0 | L9: =(B9*15%+C9*12%+D9*12%+E9*12%+F9*8%+G9*10%+H9*10%+I9*8%+J9*7%+K9*6%)*100 -> 8.7098359 | O9: 0 | P9: 45000000 | Q9: 17.5 | R9: 25 | S9: 21 | T9: 5 | U9: 6 | V9: 5000 | W9: 4 | X9: 1
A10: Center For Incubation and Business Acceleration | B10: 0 | C10: 0.0040053405 | D10: 0.32 | E10: 0.17355372 | F10: 0.26666667 | G10: 0.06122449 | H10: 0.02014652 | I10: 0.054441261 | J10: 0.28571429 | K10: 0.22222222 | L10: =(B10*15%+C10*12%+D10*12%+E10*12%+F10*8%+G10*10%+H10*10%+I10*8%+J10*7%+K10*6%)*100 -> 12.686616 | O10: 0 | P10: 80000000 | Q10: 27.5 | R10: 50 | S10: 14 | T10: 8 | U10: 15 | V10: 10000 | W10: 4 | X10: 3
A11: CIIE IIM-A | B11: 0.77777778 | C11: 0.19893191 | D11: 0.88 | E11: 0.38016529 | F11: 0.48888889 | G11: 0.28571429 | H11: 0.17582418 | I11: 0.054441261 | J11: 0.57142857 | K11: 0.44444444 | L11: =(B11*15%+C11*12%+D11*12%+E11*12%+F11*8%+G11*10%+H11*10%+I11*8%+J11*7%+K11*6%)*100 -> 44.804526 | O11: 35 | P11: 3000000000 | Q11: 62.5 | R11: 100 | S11: 24 | T11: 30 | U11: 100 | V11: 10000 | W11: 6 | X11: 5
A12: Coimbatore Innovation and Business Incubator | B12: 0 | C12: 0.012016021 | D12: 0.48 | E12: 0.21487603 | F12: 0.22222222 | G12: 0.18367347 | H12: 0.038461538 | I12: 0.083094556 | J12: 0.42857143 | K12: 0.11111111 | L12: =(B12*15%+C12*12%+D12*12%+E12*12%+F12*8%+G12*10%+H12*10%+I12*8%+J12*7%+K12*6%)*100 -> 16.813256 | O12: 0 | P12: 200000000 | Q12: 37.5 | R12: 60 | S12: 12 | T12: 20 | U12: 25 | V12: 15000 | W12: 5 | X12: 2
A13: Composites Technology Park | B13: 0 | C13: 0.0010013351 | D13: 0.08 | E13: 0 | F13: 0.48888889 | G13: 0.081632653 | H13: 0 | I13: 0.025787966 | J13: 0.14285714 | K13: 0 | L13: =(B13*15%+C13*12%+D13*12%+E13*12%+F13*8%+G13*10%+H13*10%+I13*8%+J13*7%+K13*6%)*100 -> 6.9057574 | O13: 0 | P13: 35000000 | Q13: 12.5 | R13: 8 | S13: 24 | T13: 10 | U13: 4 | V13: 5000 | W13: 3 | X13: 1
... A117: AIC RAISE | B117: 0 | C117: 0.002670227 | D117: 0.168 | E117: 0.02892562 | F117: 0.066666667 | G117: 0.040816327 | H117: 0.010989011 | I117: 0.065902579 | J117: 0.14285714 | K117: 0.11111111 | L117: =(B117*15%+C117*12%+D117*12%+E117*12%+F117*8%+G117*10%+H117*10%+I117*8%+J117*7%+K117*6%)*100 -> 5.6404242 | O117: 0 | P117: 60000000 | Q117: 18 | R117: 15 | S117: 5 | T117: 6 | U117: 10 | V117: 12000 | W117: 3 | X117: 2

Sheet Sheet3
A1: Incubator | B1: Final Score
A2: =Sheet2!A33 -> NASSCOM 10,000 Startups | B2: =Sheet2!L33 -> 57.689869
A3: =Sheet2!A11 -> CIIE IIM-A | B3: =Sheet2!L11 -> 44.804526
A4: =Sheet2!A99 -> T-Hub | B4: =Sheet2!L99 -> 43.664806
A5: =Sheet2!A101 -> SINE (Society for Innovation & Entrepreneurship) - IIT Bombay | B5: =Sheet2!L101 -> 42.152851
A6: =Sheet2!A21 -> IIT Madras Incubation Cell (IITMIC) | B6: =Sheet2!L21 -> 39.456227
A7: =Sheet2!A17 -> Foundation For Innovation And Technology Transfer, IIT-D | B7: =Sheet2!L17 -> 35.266202
A8: =Sheet2!A29 -> Life Science Incubator at IKP Knowledge Park | B8: =Sheet2!L29 -> 33.433264
A9: =Sheet2!A37 -> NSRCEL, IIM Bangalore | B9: =Sheet2!L37 -> 32.111104
A10: =Sheet2!A28 -> Kerala Startup Mission KSUM | B10: =Sheet2!L28 -> 31.865273
A11: =Sheet2!A102 -> Maker Village - Kochi | B11: =Sheet2!L102 -> 31.039531
A12: =Sheet2!A6 -> Bio Incubator at C-CAMP | B12: =Sheet2!L6 -> 27.333831
A13: =Sheet2!A19 -> IIM Calcutta Innovation Park | B13: =Sheet2!L19 -> 25.42607
A14: =Sheet2!A62 -> Venture Center | B14: =Sheet2!L62 -> 24.577254
A15: =Sheet2!A87 -> STEP- IIT Roorkee | B15: =Sheet2!L87 -> 24.033742
A16: =Sheet2!A79 -> MITCON Biotechnology Business Incubation Centre | B16: =Sheet2!L79 -> 23.52626
A17: =Sheet2!A44 -> SIDBI Innovation & Incubation Centre, IIT Kanpur | B17: =Sheet2!L44 -> 23.49925
A18: =Sheet2!A22 -> IIIT-H Foundation | B18: =Sheet2!L22 -> 21.450476
A19: =Sheet2!A2 -> Amity Innovation Incubator | B19: =Sheet2!L2 -> 20.919959
A20: =Sheet2!A100 -> IKP Eden | B20: =Sheet2!L100 -> 20.390061
A21: TBI BITS Pilani | B21: =Sheet2!L51 -> 20.244647
A22: =Sheet2!A84 -> Science & Technology Entrepreneurs Park | B22: =Sheet2!L84 -> 18.738351
A23: =Sheet2!A16 -> DLabs | B23: =Sheet2!L16 -> 17.909923
A24: =Sheet2!A3 -> Amrita TBI, Amrita VishwaVidhyapeetham | B24: =Sheet2!L3 -> 17.794814
A25: =Sheet2!A55 -> TIETS, IIT Kgp | B25: =Sheet2!L55 -> 17.774135
A26: =Sheet2!A64 -> Wadhwani Centre For Entrepreneurship Development | B26: =Sheet2!L64 -> 17.771541
A27: =Sheet2!A86 -> Society for Innovation & Development (SID) | B27: =Sheet2!L86 -> 17.713004
A28: =Sheet2!A20 -> IIT Hyderabad Incubator | B28: =Sheet2!L20 -> 17.07932
A29: =Sheet2!A31 -> Manipal University Technology Business Incubator | B29: =Sheet2!L31 -> 17.075985
A30: =Sheet2!A78 -> MITCON Biopharma | B30: =Sheet2!L78 -> 16.98096
A31: =Sheet2!A12 -> Coimbatore Innovation and Business Incubator | B31: =Sheet2!L12 -> 16.813256
A32: =Sheet2!A39 -> PSG-STEP | B32: =Sheet2!L39 -> 16.519533
A33: =Sheet2!A63 -> Villgro Innovations Foundation | B33: =Sheet2!L63 -> 16.489746
A34: =Sheet2!A27 -> International Centre for Entrepreneurship and Technology | B34: =Sheet2!L27 -> 16.456549
A35: =Sheet2!A56 -> Technology Business Incubator, KIIT University | B35: =Sheet2!L56 -> 16.422656
A36: =Sheet2!A36 -> NIT TREC-STEP | B36: =Sheet2!L36 -> 16.334479
A37: =Sheet2!A42 -> Rural Technology and Business Incubator (RTBI) | B37: =Sheet2!L42 -> 16.035603
A38: =Sheet2!A7 -> CED | B38: =Sheet2!L7 -> 15.786634
A39: =Sheet2!A30 -> Malviya Centre for Innovation Incubation & Entrepreneurship, IIT BHU | B39: =Sheet2!L30 -> 15.204607
A40: =Sheet2!A43 -> Science & Technology Park, University of Pune | B40: =Sheet2!L43 -> 15.136611
A41: =Sheet2!A81 -> niet-technology-business-incubatorNIET Technology Business Incubator | B41: =Sheet2!L81 -> 14.87633
A42: =Sheet2!A89 -> TBI at Krishnapath Incubation Society | B42: =Sheet2!L89 -> 14.360001
A43: =Sheet2!A65 -> Zone Startups India | B43: =Sheet2!L65 -> 14.301407
A44: =Sheet2!A61 -> Vellore Institute of Technology – Technology Business Incubator | B44: =Sheet2!L61 -> 14.009614
A45: =Sheet2!A49 -> STEP, Thapar University | B45: =Sheet2!L49 -> 13.913879
A46: =Sheet2!A23 -> IIT Gandhinagar Incubator | B46: =Sheet2!L23 -> 13.465045
A47: =Sheet2!A103 -> IIT Mandi Catalyst | B47: =Sheet2!L103 -> 13.152055
A48: =Sheet2!A14 -> Consumer Electronics Incubator at Cochin, Kerala | B48: =Sheet2!L14 -> 13.081066
A49: =Sheet2!A48 -> STEP-Birla Institute of Technology | B49: =Sheet2!L48 -> 12.88796
A50: =Sheet2!A98 -> Flipkart Leap | B50: =Sheet2!L98 -> 12.769536
A51: =Sheet2!A10 -> Center For Incubation and Business Acceleration | B51: =Sheet2!L10 -> 12.686616
A52: =Sheet2!A95 -> Vel Tech Technology Incubator startup-incubators | B52: =Sheet2!L95 -> 12.547933
A53: =Sheet2!A24 -> IITG – Technology Incubation Centre (IITG-TIC) | B53: =Sheet2!L24 -> 12.535186
A54: =Sheet2!A92 -> Technology Business Incubator | B54: =Sheet2!L92 -> 12.431393
A55: =Sheet2!A96 -> Patel Pharmaceutical Education & Research Development (PERD) Centre | B55: =Sheet2!L96 -> 12.172893
A56: =Sheet2!A35 -> NITK-Science Technology Entrepreneurship Park | B56: =Sheet2!L35 -> 12.102347
A57: =Sheet2!A72 -> Healthcare Technology Innovation Centre (HTIC) | B57: =Sheet2!L72 -> 11.988952
A58: =Sheet2!A70 -> Golden Jublee Women Biotech Park | B58: =Sheet2!L70 -> 11.858183
A59: =Sheet2!A32 -> MICA – Incubator | B59: =Sheet2!L32 -> 11.698082
A60: =Sheet2!A47 -> Startup Oasis Rajasthan | B60: =Sheet2!L47 -> 11.46596
A61: =Sheet2!A71 -> Gujarat State Biotechnology Mission (GSBTM) | B61: =Sheet2!L71 -> 11.443415
A62: =Sheet2!A66 -> Centre for Innovation and Entrepreneurship, IIIT-H | B62: =Sheet2!L66 -> 11.350824
A63: =Sheet2!A88 -> St.Peter’s Engineering College – Technology Business Incubator | B63: =Sheet2!L88 -> 10.97329
A64: =Sheet2!A34 -> NDBI (NID Incubator) | B64: =Sheet2!L34 -> 10.616469
A65: =Sheet2!A26 -> Innovation & Incubation Centre | B65: =Sheet2!L26 -> 10.312104
A66: =Sheet2!A77 -> KSIDC, Kerala | B66: =Sheet2!L77 -> 10.041071
A67: =Sheet2!A52 -> Technology Business Incubator, Centre for Biotechnology, Anna University | B67: =Sheet2!L52 -> 9.7871289
A68: =Sheet2!A38 -> Periyar Technology Business Incubator | B68: =Sheet2!L38 -> 9.7815892
A69: =Sheet2!A115 -> NFDI (NIFT Foundation for Design Innovation) | B69: =Sheet2!L115 -> 9.6542249
A70: =Sheet2!A107 -> IIM Udaipur Incubation Centre | B70: =Sheet2!L107 -> 9.5093149
A71: =Sheet2!A8 -> Centre For Entrepreneurship and Development | B71: =Sheet2!L8 -> 9.5007146
A72: =Sheet2!A4 -> BAIT-TBI (Bannari Amman Institute of Technology – Technology Business Incubator) | B72: =Sheet2!L4 -> 9.3269285
A73: =Sheet2!A57 -> Technology Business Incubator NIT Calicut | B73: =Sheet2!L57 -> 9.2711276
A74: =Sheet2!A40 -> Sardar Patel Technology Business Incubator | B74: =Sheet2!L40 -> 9.2586522
A75: =Sheet2!A5 -> Bihar Entrepreneurs Association (BEA) | B75: =Sheet2!L5 -> 9.2081104
A76: =Sheet2!A53 -> Technology Business Incubator, Graphic Era University, Dehradun | B76: =Sheet2!L53 -> 9.1309558
A77: =Sheet2!A9 -> CET – Technology Business Incubator | B77: =Sheet2!L9 -> 8.7098359
A78: =Sheet2!A69 -> Ekta Incubation Center, Maulana Kalam Azad University of Technology | B78: =Sheet2!L69 -> 8.6641696
A79: =Sheet2!A67 -> Development of Entrepreneurs Through Incubation (DETI@ACE) | B79: =Sheet2!L67 -> 8.5519324
A80: =Sheet2!A58 -> Technology Business Incubator for Medical Devices & Biomaterials | B80: =Sheet2!L58 -> 8.1968147
A81: =Sheet2!A41 -> Sathyabama University-TBI | B81: =Sheet2!L41 -> 7.9108985
A82: =Sheet2!A90 -> Technology Incubation and Development of Entrepreneurship | B82: =Sheet2!L90 -> 7.8634956
A83: =Sheet2!A59 -> University of Madras, Technology Business Incubator | B83: =Sheet2!L59 -> 7.6745611
A84: =Sheet2!A25 -> Incube Ventures | B84: =Sheet2!L25 -> 7.5629206
A85: =Sheet2!A68 -> DKTE Technology Business Incubator | B85: =Sheet2!L68 -> 7.5193127
A86: =Sheet2!A91 -> Technology Innovation and Incubation Centre | B86: =Sheet2!L91 -> 7.4836346
A87: =Sheet2!A85 -> Shri Shankaracharya Technical Campus | B87: =Sheet2!L85 -> 7.4750509
A88: =Sheet2!A45 -> SMVDU TBIC | B88: =Sheet2!L45 -> 7.4320123
A89: =Sheet2!A60 -> UnLtd Hyderabad | B89: =Sheet2!L60 -> 7.2560098
A90: =Sheet2!A76 -> Incubation Centre, IIT- Patna | B90: =Sheet2!L76 -> 7.0727758
A91: =Sheet2!A94 -> Trident Business Incubator | B91: =Sheet2!L94 -> 6.9145854
A92: =Sheet2!A13 -> Composites Technology Park | B92: =Sheet2!L13 -> 6.9057574
A93: =Sheet2!A46 -> Society for Innovation & Entrepreneurship in Dairying (SINED) Technology Business Incubator | B93: =Sheet2!L46 -> 6.8798636
A94: =Sheet2!A104 -> AIC Pinnacle | B94: =Sheet2!L104 -> 6.5447614
A95: =Sheet2!A50 -> Tagore Centre for Green Technology Business Incubation | B95: =Sheet2!L50 -> 6.4107843
A96: =Sheet2!A15 -> DA-IICT Incubator CEID | B96: =Sheet2!L15 -> 6.3782192
A97: =Sheet2!A114 -> AIC Banasthali | B97: =Sheet2!L114 -> 6.2217893
A98: =Sheet2!A82 -> NSIC Technical Services Centre | B98: =Sheet2!L82 -> 6.2115401
A99: =Sheet2!A105 -> AIC-CCMB | B99: =Sheet2!L105 -> 5.791944
A100: =Sheet2!A117 -> AIC RAISE | B100: =Sheet2!L117 -> 5.6404242
...
